src/rodan/__init__.py
rodan-0.0.1.dist-info/LICENSE
rodan-0.0.1.dist-info/METADATA
rodan-0.0.1.dist-info/WHEEL
rodan-0.0.1.dist-info/top_level.txt
rodan-0.0.1.dist-info/RECORD
