Metadata-Version: 2.1
Name: rodan
Version: 0.0.1
Summary: Advanced Deep Learning Library
Home-page: https://github.com/hoangtnm/rodan
Author: Hoang N.M. Tran
Author-email: UNKNOWN
License: Apache License, Version 2.0
Platform: UNKNOWN
Classifier: Intended Audience :: Developers
Classifier: Intended Audience :: Education
Classifier: Topic :: Scientific/Engineering
Classifier: Topic :: Scientific/Engineering :: Mathematics
Classifier: Topic :: Scientific/Engineering :: Artificial Intelligence
Classifier: Topic :: Software Development
Classifier: Topic :: Software Development :: Libraries
Classifier: Topic :: Software Development :: Libraries :: Python Modules
Classifier: Programming Language :: Python :: 3
Requires-Dist: torch (>=1.7)
Requires-Dist: torchvision (>=0.8)
Requires-Dist: torchaudio
Requires-Dist: tensorflow (>=2.4)
Requires-Dist: Matplotlib
Requires-Dist: Cython
